starception/__init__.py
starception/exception_handler.py
starception/py.typed
starception/templates/code_dark.css
starception/templates/code_light.css
starception/templates/code_snippet.html
starception/templates/dark.css
starception/templates/frame_line.html
starception/templates/icon_google.svg
starception/templates/icon_moon.svg
starception/templates/icon_stackoverflow.svg
starception/templates/icon_sun.svg
starception/templates/icon_sun_moon.svg
starception/templates/index.html
starception/templates/lib.html
starception/templates/scripts.js
starception/templates/styles.css
starception-1.2.1.dist-info/LICENSE
starception-1.2.1.dist-info/METADATA
starception-1.2.1.dist-info/WHEEL
starception-1.2.1.dist-info/RECORD
