Metadata-Version: 2.1
Name: starception
Version: 1.2.1
Summary: Beautiful debugging page for Starlette apps.
Home-page: https://github.com/alex-oleshkevich/starception
License: MIT
Author: Alex Oleshkevich
Author-email: alex.oleshkevich@gmail.com
Requires-Python: >=3.8,<4.0
Classifier: Development Status :: 5 - Production/Stable
Classifier: Environment :: Web Environment
Classifier: Intended Audience :: Developers
Classifier: License :: OSI Approved :: MIT License
Classifier: Operating System :: OS Independent
Classifier: Programming Language :: Python :: 3
Classifier: Programming Language :: Python :: 3.8
Classifier: Programming Language :: Python :: 3.9
Classifier: Programming Language :: Python :: 3.10
Classifier: Programming Language :: Python :: 3.11
Classifier: Topic :: Software Development :: Libraries :: Python Modules
Classifier: Typing :: Typed
Provides-Extra: highlight
Requires-Dist: Jinja2 (>=3,<4)
Requires-Dist: MarkupSafe (>=2,<3)
Requires-Dist: typing_extensions (>=4.4,<5.0)
Project-URL: Documentation, https://github.com/alex-oleshkevich/starception
Project-URL: Repository, https://github.com/alex-oleshkevich/starception
